AnhengShentouGongjiHongduiBaikequanshuXiaFix1/README.md
AnhengShentouGongjiHongduiBaikequanshuXiaFix1/__init__.py
AnhengShentouGongjiHongduiBaikequanshuXiaFix1/__main__.py
AnhengShentouGongjiHongduiBaikequanshuXiaFix1/file.pdf
AnhengShentouGongjiHongduiBaikequanshuXiaFix1/index.html
anheng_shentou_gongji_hongdui_baikequanshu_xia_fix1-2025.3.23.1.dist-info/METADATA
anheng_shentou_gongji_hongdui_baikequanshu_xia_fix1-2025.3.23.1.dist-info/WHEEL
anheng_shentou_gongji_hongdui_baikequanshu_xia_fix1-2025.3.23.1.dist-info/entry_points.txt
anheng_shentou_gongji_hongdui_baikequanshu_xia_fix1-2025.3.23.1.dist-info/top_level.txt
anheng_shentou_gongji_hongdui_baikequanshu_xia_fix1-2025.3.23.1.dist-info/RECORD
